{
  "fps": 12,
  "offset": {
    "x": -40,
    "y": -40
  },
  "hitbox": {
    "x": 0,
    "y": 0,
    "w": 80,
    "h": 80
  },
  "labels": [
    {
      "name": "anim_idle",
      "start": 0,
      "end": 16
    },
    {
      "name": "anim_blink_twitch",
      "start": 17,
      "end": 21
    },
    {
      "name": "anim_blink_twice",
      "start": 23,
      "end": 29
    },
    {
      "name": "anim_blink_thrice",
      "start": 31,
      "end": 41
    }

  ],
  "families": [
    { "child": "anim_blink_twitch", "parent": "anim_face", "FullInherit": true },
    { "child": "anim_blink_twice", "parent": "anim_face", "FullInherit": true },
    { "child": "anim_blink_thrice", "parent": "anim_face", "FullInherit": true }
  ],
    "tracks":[
        {
            "name":"_ground",
            "transforms":[
                {
                    "f":-1
                },
                {},
                {},
                {},
                {},
                {},
                {},
                {},
                {},
                {},
                {},
                {},
                {},
                {},
                {},
                {},
                {},
                {},
                {},
                {},
                {},
                {},
                {},
                {},
                {},
                {},
                {},
                {},
                {},
                {},
                {},
                {},
                {},
                {},
                {},
                {},
                {},
                {},
                {},
                {},
                {},
                {},
                {},
                {
                    "x":44.8,
                    "y":75.5,
                    "f":0
                },
                {
                    "x":27.6
                },
                {
                    "x":8.9
                },
                {
                    "x":-11.3
                },
                {
                    "x":-31.5
                },
                {
                    "x":-50.2
                },
                {
                    "x":-67.4
                },
                {
                    "x":-84.6
                },
                {
                    "x":-103.4
                },
                {
                    "x":-123.6
                },
                {
                    "x":-143.8
                },
                {
                    "x":-162.5
                },
                {
                    "x":-179.8
                }
            ]
        },
        {
            "name":"anim_idle",
            "transforms":[
                {},
                {},
                {},
                {},
                {},
                {},
                {},
                {},
                {},
                {},
                {},
                {},
                {},
                {},
                {},
                {},
                {},
                {
                    "f":-1
                },
                {},
                {},
                {},
                {},
                {},
                {},
                {},
                {},
                {},
                {},
                {},
                {},
                {},
                {},
                {},
                {},
                {},
                {},
                {},
                {},
                {},
                {},
                {},
                {},
                {},
                {},
                {},
                {},
                {},
                {},
                {},
                {},
                {},
                {},
                {},
                {},
                {},
                {}
            ]
        },
        {
            "name":"anim_face",
            "transforms":[
                {
                    "x":6.9,
                    "y":3.6,
                    "sx":0.7,
                    "sy":0.719,
                    "i":"IMAGE_REANIM_WALLNUT_BODY"
                },
                {
                    "x":6,
                    "y":4.8,
                    "kx":-0.7,
                    "ky":-0.7,
                    "sy":0.711
                },
                {
                    "x":5.2,
                    "y":6.2,
                    "kx":-1.4,
                    "ky":-1.4,
                    "sy":0.702
                },
                {
                    "x":4.3,
                    "y":7.5,
                    "kx":-2.2,
                    "ky":-2.1,
                    "sy":0.694
                },
                {
                    "x":3.5,
                    "y":8.8,
                    "kx":-2.9,
                    "ky":-2.9,
                    "sy":0.686
                },
                {
                    "x":4.3,
                    "y":7.5,
                    "kx":-2.2,
                    "ky":-2.2,
                    "sy":0.694
                },
                {
                    "x":5.2,
                    "y":6.2,
                    "kx":-1.4,
                    "ky":-1.4,
                    "sy":0.702
                },
                {
                    "x":6,
                    "y":4.8,
                    "kx":-0.6,
                    "ky":-0.6,
                    "sy":0.71
                },
                {
                    "x":7,
                    "y":3.6,
                    "kx":0,
                    "ky":0,
                    "sy":0.719
                },
                {
                    "x":7.9,
                    "y":3.9,
                    "kx":0.8,
                    "ky":0.7,
                    "sy":0.711
                },
                {
                    "x":8.8,
                    "y":4.3,
                    "kx":1.5,
                    "ky":1.5,
                    "sy":0.702
                },
                {
                    "x":9.8,
                    "y":4.6,
                    "kx":2.3,
                    "ky":2.3,
                    "sy":0.694
                },
                {
                    "x":10.5,
                    "y":4.9,
                    "kx":3,
                    "ky":3,
                    "sy":0.686
                },
                {
                    "x":9.6,
                    "y":4.5,
                    "kx":2.3,
                    "ky":2.3,
                    "sy":0.694
                },
                {
                    "x":8.7,
                    "y":4.2,
                    "kx":1.5,
                    "ky":1.5,
                    "sy":0.702
                },
                {
                    "x":7.8,
                    "y":3.7,
                    "kx":0.8,
                    "ky":0.8,
                    "sy":0.711
                },
                {
                    "x":7,
                    "y":3.5,
                    "kx":0,
                    "ky":0,
                    "sy":0.719
                },
                {
                    "f":-1
                },
                {},
                {},
                {},
                {},
                {},
                {},
                {},
                {},
                {},
                {},
                {},
                {},
                {},
                {},
                {},
                {},
                {},
                {},
                {},
                {},
                {},
                {},
                {},
                {},
                {},
                {
                    "x":7.3,
                    "y":3.6,
                    "f":0
                },
                {
                    "x":29.2,
                    "y":-7.4,
                    "kx":27.6,
                    "ky":27.6,
                    "sx":0.699,
                    "sy":0.718
                },
                {
                    "x":56.7,
                    "y":-6.3,
                    "kx":57.7,
                    "ky":57.7
                },
                {
                    "x":82.5,
                    "y":10.1,
                    "kx":90,
                    "ky":90,
                    "sx":0.7,
                    "sy":0.719
                },
                {
                    "x":96.2,
                    "y":33.1,
                    "kx":122.3,
                    "ky":122.3,
                    "sx":0.699,
                    "sy":0.718
                },
                {
                    "x":94.6,
                    "y":57.9,
                    "kx":152.4,
                    "ky":152.4
                },
                {
                    "x":81.1,
                    "y":76.7,
                    "kx":180,
                    "ky":180,
                    "sx":0.7,
                    "sy":0.719
                },
                {
                    "x":59.1,
                    "y":91.3,
                    "kx":207.6,
                    "ky":207.6,
                    "sx":0.699,
                    "sy":0.718
                },
                {
                    "x":31.5,
                    "y":94.1,
                    "kx":237.7,
                    "ky":237.7
                },
                {
                    "x":5.7,
                    "y":81.7,
                    "kx":270,
                    "ky":270,
                    "sx":0.7,
                    "sy":0.719
                },
                {
                    "x":-7.9,
                    "y":54.5,
                    "kx":302.3,
                    "ky":302.3,
                    "sx":0.699,
                    "sy":0.718
                },
                {
                    "x":-6.3,
                    "y":25.9,
                    "kx":332.4,
                    "ky":332.4
                },
                {
                    "x":6.9,
                    "y":3.6,
                    "kx":360,
                    "ky":360,
                    "sx":0.7,
                    "sy":0.719
                }
            ]
        },
        {
            "name":"anim_blink_twitch",
            "transforms":[
                {
                    "f":-1
                },
                {},
                {},
                {},
                {},
                {},
                {},
                {},
                {},
                {},
                {},
                {},
                {},
                {},
                {},
                {},
                {},
                {
                    "x":29.2,
                    "y":35.6,
                    "sx":0.7,
                    "sy":0.7,
                    "f":0,
                    "i":"IMAGE_REANIM_WALLNUT_TWITCH"
                },
                {
                    "y":34.2
                },
                {
                    "y":35.6
                },
                {
                    "y":34.2
                },
                {
                    "y":35.6
                },
                {
                    "f":-1
                },
                {},
                {},
                {},
                {},
                {},
                {},
                {},
                {},
                {},
                {},
                {},
                {},
                {},
                {},
                {},
                {},
                {},
                {},
                {},
                {},
                {},
                {},
                {},
                {},
                {},
                {},
                {},
                {},
                {},
                {},
                {},
                {},
                {}
            ]
        },
        {
            "name":"anim_blink_twice",
            "transforms":[
                {
                    "f":-1
                },
                {},
                {},
                {},
                {},
                {},
                {},
                {},
                {},
                {},
                {},
                {},
                {},
                {},
                {},
                {},
                {},
                {},
                {},
                {},
                {},
                {},
                {},
                {
                    "x":28,
                    "y":21.6,
                    "sx":0.7,
                    "sy":0.7,
                    "f":0,
                    "i":"IMAGE_REANIM_WALLNUT_BLINK1"
                },
                {
                    "y":21.8,
                    "i":"IMAGE_REANIM_WALLNUT_BLINK2"
                },
                {
                    "y":21.6,
                    "i":"IMAGE_REANIM_WALLNUT_BLINK1"
                },
                {
                    "f":-1
                },
                {
                    "f":0
                },
                {
                    "y":21.8,
                    "i":"IMAGE_REANIM_WALLNUT_BLINK2"
                },
                {
                    "y":21.6,
                    "i":"IMAGE_REANIM_WALLNUT_BLINK1"
                },
                {
                    "f":-1
                },
                {},
                {},
                {},
                {},
                {},
                {},
                {},
                {},
                {},
                {},
                {},
                {},
                {},
                {},
                {},
                {},
                {},
                {},
                {},
                {},
                {},
                {},
                {},
                {},
                {}
            ]
        },
        {
            "name":"anim_blink_thrice",
            "transforms":[
                {
                    "f":-1
                },
                {},
                {},
                {},
                {},
                {},
                {},
                {},
                {},
                {},
                {},
                {},
                {},
                {},
                {},
                {},
                {},
                {},
                {},
                {},
                {},
                {},
                {},
                {},
                {},
                {},
                {},
                {},
                {},
                {},
                {},
                {
                    "x":28,
                    "y":21.6,
                    "sx":0.7,
                    "sy":0.7,
                    "f":0,
                    "i":"IMAGE_REANIM_WALLNUT_BLINK1"
                },
                {
                    "y":21.8,
                    "i":"IMAGE_REANIM_WALLNUT_BLINK2"
                },
                {
                    "y":21.6,
                    "i":"IMAGE_REANIM_WALLNUT_BLINK1"
                },
                {
                    "f":-1
                },
                {
                    "f":0
                },
                {
                    "y":21.8,
                    "i":"IMAGE_REANIM_WALLNUT_BLINK2"
                },
                {
                    "y":21.6,
                    "i":"IMAGE_REANIM_WALLNUT_BLINK1"
                },
                {
                    "f":-1
                },
                {
                    "f":0
                },
                {
                    "y":21.8,
                    "i":"IMAGE_REANIM_WALLNUT_BLINK2"
                },
                {
                    "y":21.6,
                    "i":"IMAGE_REANIM_WALLNUT_BLINK1"
                },
                {
                    "f":-1
                },
                {},
                {},
                {},
                {},
                {},
                {},
                {},
                {},
                {},
                {},
                {},
                {},
                {}
            ]
        }
    ]
}
